pip_example/__init__.py
pip_example/example.py
pip_example-0.0.2.dist-info/METADATA
pip_example-0.0.2.dist-info/WHEEL
pip_example-0.0.2.dist-info/top_level.txt
pip_example-0.0.2.dist-info/RECORD
